pytest_subprocessed/__init__.py
pytest_subprocessed-1.0.1.dist-info/LICENSE
pytest_subprocessed-1.0.1.dist-info/METADATA
pytest_subprocessed-1.0.1.dist-info/WHEEL
pytest_subprocessed-1.0.1.dist-info/entry_points.txt
pytest_subprocessed-1.0.1.dist-info/top_level.txt
pytest_subprocessed-1.0.1.dist-info/RECORD
